{
    "root": {
        "data": {
            "body": "Pada 1 Mei 2025 diperingati Hari Buruh Internasional (May Day). Ini merupakan momen penting yang dirayakan oleh para pekerja di berbagai belahan dunia sebagai simbol perjuangan atas hak-hak buruh dan keadilan sosial di tempat kerja.Di Indonesia, peringatan ini tak hanya diisi dengan aksi damai dan kegiatan seremonial, tapi juga jadi momentum refleksi atas kontribusi besar para pekerja terhadap kemajuan bangsa.Namun, pertanyaan yang sering muncul menjelang tanggal tersebut adalah: apakah Hari Buruh Internasional pada tanggal 1 Mei 2025 termasuk hari libur nasional?\nSCROLL TO CONTINUE WITH CONTENT\nJawabannya: ya. Peringatan Hari Buruh Internasional pada Kamis, 1 Mei 2025 adalah hari libur nasional. Hal ini tercantum dalam Surat Keputusan Bersama (SKB) 3 Menteri tentang Hari Libur Nasional dan Cuti Bersama Tahun 2025.Dengan demikian, aktivitas perkantoran, sekolah, hingga instansi pemerintahan akan diliburkan, kecuali sektor-sektor esensial seperti layanan kesehatan, transportasi, keamanan, dan pelayanan publik tertentu yang tetap berjalan selama hari libur.Penetapan 1 Mei sebagai Hari Buruh Internasional sudah diakui secara global sejak tahun 1889 oleh Kongres Buruh Internasional di Paris. Hari ini sebagai bentuk penghormatan terhadap perjuangan buruh di Chicago, Amerika Serikat.Di Indonesia, tanggal 1 Mei resmi ditetapkan sebagai hari libur nasional berdasarkan Keputusan Presiden (Keppres) Nomor 24 Tahun 2013. Langkah ini merupakan pengakuan negara atas pentingnya kontribusi buruh dalam roda pembangunan nasional.Selain itu, bulan Mei 2025 juga menawarkan beberapa hari libur nasional lainnya, termasuk Hari Raya Waisak 2569 BE dan Kenaikan Yesus Kristus, yang dapat dimanfaatkan untuk merencanakan waktu berkualitas bersama orang terkasih .Berikut ini daftar tanggal merah libur nasional dan cuti bersama:Berikut ini daftar tanggal long weekend dan rekomendasi cutinya:",
            "gambar": "https://akcdn.detik.net.id/visual/2025/04/12/kalender-1744422633200_43.jpeg?w=250&q=90",
            "judul": "Hari Buruh 1 Mei 2025 Apakah Libur? Cek Info Tanggal Merahnya!",
            "link": "https://news.detik.com/berita/d-7885207/hari-buruh-1-mei-2025-apakah-libur-cek-info-tanggal-merahnya",
            "waktu": "Jumat, 25 Apr 2025 11:25 WIB"
        }
    }
}